{
  "kind": "singleType",
  "collectionName": "featured_projects_set",
  "info": {
    "singularName": "featured-project",
    "pluralName": "featured-projects-set",
    "displayName": "Featured Projects",
    "description": ""
  },
  "options": {
    "draftAndPublish": false
  },
  "pluginOptions": {},
  "attributes": {
    "Project1": {
      "type": "relation",
      "relation": "oneToOne",
      "target": "api::project.project"
    },
    "Project2": {
      "type": "relation",
      "relation": "oneToOne",
      "target": "api::project.project"
    },
    "Project3": {
      "type": "relation",
      "relation": "oneToOne",
      "target": "api::project.project"
    }
  }
}
